{
    "title": "davidmac.pro",
    "url": "https://davidmac.pro",
    "description": "Tech enthusiasm from down-under",
    "defaultFeaturedImage": "/assets/img/default-featured-image.png",
    "themeColor": "#EDF2F7",
    "utterancesRepo": "towerofpower256/davidmac.pro",
    "feed": {
      "subtitle": "Tech enthusiasm from down-under",
      "filename": "feed.xml",
      "path": "/feed/feed.xml",
      "id": "https://davidmac.pro/"
    },
    "jsonfeed": {
      "path": "/feed/feed.json",
      "url": "https://davidmac.pro/feed/feed.json"
    },
    "author": {
      "name": "David McDonald",
      "url": "https://davidmac.pro/"
    },
    "social": {
      "github": "https://github.com/towerofpower256",
      "linkedin": "https://www.linkedin.com/in/davidmcdonaldbrisbane/",
      "servicenow": "https://community.servicenow.com/community?id=community_user_profile&user=39d11221dbd81fc09c9ffb651f9619cd"
    },
    "splash": {
      "name": "David McDonald",
      "description": "Tech enthusiasm from down-under",
      "img": ""
    }
  }